monocdk/__init__.py
monocdk/py.typed
monocdk/_jsii/__init__.py
monocdk/_jsii/monocdk@1.204.0.jsii.tgz
monocdk/alexa_ask/__init__.py
monocdk/app_delivery/__init__.py
monocdk/assertions/__init__.py
monocdk/assets/__init__.py
monocdk/aws_accessanalyzer/__init__.py
monocdk/aws_acmpca/__init__.py
monocdk/aws_amazonmq/__init__.py
monocdk/aws_amplify/__init__.py
monocdk/aws_amplifyuibuilder/__init__.py
monocdk/aws_apigateway/__init__.py
monocdk/aws_apigatewayv2/__init__.py
monocdk/aws_apigatewayv2_authorizers/__init__.py
monocdk/aws_apigatewayv2_integrations/__init__.py
monocdk/aws_appconfig/__init__.py
monocdk/aws_appflow/__init__.py
monocdk/aws_appintegrations/__init__.py
monocdk/aws_applicationautoscaling/__init__.py
monocdk/aws_applicationinsights/__init__.py
monocdk/aws_appmesh/__init__.py
monocdk/aws_apprunner/__init__.py
monocdk/aws_appstream/__init__.py
monocdk/aws_appsync/__init__.py
monocdk/aws_aps/__init__.py
monocdk/aws_athena/__init__.py
monocdk/aws_auditmanager/__init__.py
monocdk/aws_autoscaling/__init__.py
monocdk/aws_autoscaling_common/__init__.py
monocdk/aws_autoscaling_hooktargets/__init__.py
monocdk/aws_autoscalingplans/__init__.py
monocdk/aws_backup/__init__.py
monocdk/aws_backupgateway/__init__.py
monocdk/aws_batch/__init__.py
monocdk/aws_billingconductor/__init__.py
monocdk/aws_budgets/__init__.py
monocdk/aws_cassandra/__init__.py
monocdk/aws_ce/__init__.py
monocdk/aws_certificatemanager/__init__.py
monocdk/aws_chatbot/__init__.py
monocdk/aws_cloud9/__init__.py
monocdk/aws_cloudformation/__init__.py
monocdk/aws_cloudfront/__init__.py
monocdk/aws_cloudfront/experimental/__init__.py
monocdk/aws_cloudfront_origins/__init__.py
monocdk/aws_cloudtrail/__init__.py
monocdk/aws_cloudwatch/__init__.py
monocdk/aws_cloudwatch_actions/__init__.py
monocdk/aws_codeartifact/__init__.py
monocdk/aws_codebuild/__init__.py
monocdk/aws_codecommit/__init__.py
monocdk/aws_codedeploy/__init__.py
monocdk/aws_codeguruprofiler/__init__.py
monocdk-1.204.0.dist-info/LICENSE
monocdk-1.204.0.dist-info/METADATA
monocdk-1.204.0.dist-info/NOTICE
monocdk-1.204.0.dist-info/WHEEL
monocdk-1.204.0.dist-info/top_level.txt
monocdk-1.204.0.dist-info/RECORD
